{"name":"fec65fe1-0e97-4752-969f-d7d589d39e0b","id":"/providers/Microsoft.Flow/flows/fec65fe1-0e97-4752-969f-d7d589d39e0b","type":"Microsoft.Flow/flows","properties":{"apiId":"/providers/Microsoft.PowerApps/apis/shared_logicflows","displayName":"MySend","definition":{"metadata":{"workflowEntityId":null,"processAdvisorMetadata":null,"flowChargedByPaygo":null,"flowclientsuspensionreason":"None","flowclientsuspensiontime":null,"flowclientsuspensionreasondetails":null,"creator":{"id":"be888b31-1ab2-40ca-b928-6098ae00ba37","type":"User","tenantId":"3018ecb9-2438-4581-b036-4b625dac9579"},"provisioningMethod":"FromDefinition","failureAlertSubscription":true,"clientLastModifiedTime":"2024-08-13T08:44:16.0817345Z","connectionKeySavedTimeKey":"2024-08-13T08:44:16.0817345Z"},"$schema":"https://schema.management.azure.com/providers/Microsoft.Logic/schemas/2016-06-01/workflowdefinition.json#","contentVersion":"1.0.0.0","parameters":{"$connections":{"defaultValue":{},"type":"Object"},"$authentication":{"defaultValue":{},"type":"SecureObject"}},"triggers":{"manual":{"metadata":{"operationMetadataId":"28f7cb2a-30d5-4592-8548-5bdd76210aa8"},"type":"Request","kind":"PowerAppV2","inputs":{"schema":{"type":"object","properties":{"text":{"title":"Nama Pegawai","type":"string","x-ms-dynamically-added":true,"description":"Please enter your input","x-ms-content-hint":"TEXT"},"text_1":{"title":"Email","type":"string","x-ms-dynamically-added":true,"description":"Please enter your input","x-ms-content-hint":"TEXT"},"text_2":{"title":"Mulai","type":"string","x-ms-dynamically-added":true,"description":"Please enter your input","x-ms-content-hint":"TEXT"},"text_3":{"title":"Nama Mobil","type":"string","x-ms-dynamically-added":true,"description":"Please enter your input","x-ms-content-hint":"TEXT"},"text_4":{"title":"Jenis","type":"string","x-ms-dynamically-added":true,"description":"Please enter your input","x-ms-content-hint":"TEXT"},"text_5":{"title":"Vendor","type":"string","x-ms-dynamically-added":true,"description":"Please enter your input","x-ms-content-hint":"TEXT"},"text_6":{"title":"Tipe","type":"string","x-ms-dynamically-added":true,"description":"Please enter your input","x-ms-content-hint":"TEXT"},"text_7":{"title":"Kontrak Pemeliharaan","type":"string","x-ms-dynamically-added":true,"description":"Please enter your input","x-ms-content-hint":"TEXT"},"text_8":{"title":"Keterangan","type":"string","x-ms-dynamically-added":true,"description":"Please enter your input","x-ms-content-hint":"TEXT"},"text_9":{"title":"Nomor Pegawai","type":"string","x-ms-dynamically-added":true,"description":"Please enter your input","x-ms-content-hint":"TEXT"},"text_10":{"title":"Department","type":"string","x-ms-dynamically-added":true,"description":"Please enter your input","x-ms-content-hint":"TEXT"},"text_11":{"title":"Lokasi","type":"string","x-ms-dynamically-added":true,"description":"Please enter your input","x-ms-content-hint":"TEXT"},"text_12":{"title":"Read","type":"string","x-ms-dynamically-added":true,"description":"Please enter your input","x-ms-content-hint":"TEXT"},"text_13":{"title":"Submission Time","type":"string","x-ms-dynamically-added":true,"description":"Please enter your input","x-ms-content-hint":"TEXT"},"text_14":{"title":"No Telp","type":"string","x-ms-dynamically-added":true,"description":"Please enter your input","x-ms-content-hint":"TEXT"}},"required":["text","text_1","text_2","text_3","text_4","text_5","text_6","text_7","text_8","text_9","text_10","text_11","text_12","text_13","text_14"]}}}},"actions":{"Initialize_variable_2":{"runAfter":{},"metadata":{"operationMetadataId":"f3530495-59ec-4b35-8124-1c4f7402e4ba"},"type":"InitializeVariable","inputs":{"variables":[{"name":"Nama Pegawai","type":"string","value":"@triggerBody()['text']"}]}},"Initialize_variable_8":{"runAfter":{"Initialize_variable_2":["Succeeded"]},"metadata":{"operationMetadataId":"2956dcbd-e63b-4891-9f80-7cc76d42a83e"},"type":"InitializeVariable","inputs":{"variables":[{"name":"Alamat Email","type":"string","value":"@triggerBody()['text_1']"}]}},"Initialize_variable_9":{"runAfter":{"Initialize_variable_8":["Succeeded"]},"metadata":{"operationMetadataId":"3f13b63f-adc0-4104-95ed-2d9b25703765"},"type":"InitializeVariable","inputs":{"variables":[{"name":"Mulai","type":"string","value":"@triggerBody()['text_2']"}]}},"Create_item":{"runAfter":{"Initialize_variable_15":["Succeeded"]},"metadata":{"operationMetadataId":"da2ff0a6-60ac-4acf-a5b1-5ae895099315"},"type":"OpenApiConnection","inputs":{"host":{"apiId":"/providers/Microsoft.PowerApps/apis/shared_sharepointonline","connectionName":"shared_sharepointonline","operationId":"PostItem"},"parameters":{"dataset":"https://studentssbac.sharepoint.com/sites/BankIndonesia","table":"5da070aa-d344-4a58-8b57-808cdb2b562e","item/Title":"@variables('Nama Mobil')","item/NamaMobil":"@variables('Nama Pegawai')","item/Departemen":"@variables('Department')","item/NomorPegawai":"@variables('Nomor pegawai')","item/Lokasi0":"@variables('Lokasi')","item/AlamatEmail":"@variables('Jenis')","item/NomorTiket":"@variables('Vendor')","item/Jenis":"@variables('Tipe')","item/Lokasi":"@variables('Alamat Email')","item/Mulai":"@variables('Mulai')","item/KontrakPemeliharaan":"@variables('Kontrak Pemeliharaan')","item/Keterangan":"@variables('Keterangan')","item/Status":"@variables('Read')","item/SubmissionTime":"@variables('Submission Time')","item/NomorTelepon":"@variables('Telly')"},"authentication":{"value":"@json(decodeBase64(triggerOutputs().headers['X-MS-APIM-Tokens']))['$ConnectionKey']","type":"Raw"}}},"Initialize_variable":{"runAfter":{"Initialize_variable_9":["Succeeded"]},"metadata":{"operationMetadataId":"e349c15e-80e7-4182-ba6a-4ad910fbd9a4"},"type":"InitializeVariable","inputs":{"variables":[{"name":"Nama Mobil","type":"string","value":"@triggerBody()['text_3']"}]}},"Initialize_variable_3":{"runAfter":{"Initialize_variable":["Succeeded"]},"metadata":{"operationMetadataId":"94edf9c5-10a5-42f6-b66a-8ad7259ec52f"},"type":"InitializeVariable","inputs":{"variables":[{"name":"Jenis","type":"string","value":"@triggerBody()['text_4']"}]}},"Initialize_variable_4":{"runAfter":{"Initialize_variable_3":["Succeeded"]},"metadata":{"operationMetadataId":"d9564c39-ac38-4dfb-9f5c-7a959b86fb92"},"type":"InitializeVariable","inputs":{"variables":[{"name":"Vendor","type":"string","value":"@triggerBody()['text_5']"}]}},"Initialize_variable_5":{"runAfter":{"Initialize_variable_4":["Succeeded"]},"metadata":{"operationMetadataId":"c4a326ee-497e-4739-a886-997380885fc6"},"type":"InitializeVariable","inputs":{"variables":[{"name":"Tipe","type":"string","value":"@triggerBody()['text_6']"}]}},"Initialize_variable_6":{"runAfter":{"Initialize_variable_5":["Succeeded"]},"metadata":{"operationMetadataId":"1cd34907-b72e-4729-a8eb-1528093bd81f"},"type":"InitializeVariable","inputs":{"variables":[{"name":"Kontrak Pemeliharaan","type":"string","value":"@triggerBody()['text_7']"}]}},"Initialize_variable_7":{"runAfter":{"Initialize_variable_6":["Succeeded"]},"metadata":{"operationMetadataId":"91ae97b4-aece-43e9-b354-446fb499ecdb"},"type":"InitializeVariable","inputs":{"variables":[{"name":"Keterangan","type":"string","value":"@triggerBody()['text_8']"}]}},"Initialize_variable_10":{"runAfter":{"Initialize_variable_7":["Succeeded"]},"metadata":{"operationMetadataId":"8f67a556-0cc9-49d4-8941-ec8c5d460b5a"},"type":"InitializeVariable","inputs":{"variables":[{"name":"Nomor pegawai","type":"string","value":"@triggerBody()['text_9']"}]}},"Initialize_variable_11":{"runAfter":{"Initialize_variable_10":["Succeeded"]},"metadata":{"operationMetadataId":"0b7b0cb3-569a-4357-9568-fe159a38f785"},"type":"InitializeVariable","inputs":{"variables":[{"name":"Department","type":"string","value":"@triggerBody()['text_10']"}]}},"Initialize_variable_12":{"runAfter":{"Initialize_variable_11":["Succeeded"]},"metadata":{"operationMetadataId":"3ea91f83-8fe9-45e5-834f-1784074b0d47"},"type":"InitializeVariable","inputs":{"variables":[{"name":"Lokasi","type":"string","value":"@triggerBody()['text_11']"}]}},"Initialize_variable_13":{"runAfter":{"Initialize_variable_12":["Succeeded"]},"metadata":{"operationMetadataId":"20f3689b-b708-4d77-b8b6-f83740ed7136"},"type":"InitializeVariable","inputs":{"variables":[{"name":"Read","type":"string","value":"@triggerBody()['text_12']"}]}},"Send_an_email_(V2)":{"runAfter":{"Create_item":["Succeeded"]},"metadata":{"operationMetadataId":"a89f4f9b-7983-46a2-8e4f-01388b96620f"},"type":"OpenApiConnection","inputs":{"host":{"apiId":"/providers/Microsoft.PowerApps/apis/shared_office365","connectionName":"shared_office365","operationId":"SendEmailV2"},"parameters":{"emailMessage/To":"ryufath.soepeno@my.sampoernauniversity.ac.id","emailMessage/Subject":"Invoice @{variables('Nama Mobil')} - @{variables('Nama Pegawai')}","emailMessage/Body":"<p>Berikut adalah invoice mobil yang Anda telah ajukan:<br>\nNama Pegawai: @{variables('Nama Pegawai')} - @{variables('Nomor pegawai')}<br>\nNama Mobil: @{variables('Nama Mobil')}<br>\nAjuan Tanggal Mulai: @{variables('Mulai')}<br>\nLokasi: @{variables('Lokasi')}<br>\nTipe: @{variables('Tipe')}<br>\n<br>\nAnda diharap untuk menunggu konfirmasi pengajuan kendaraan dari satker DLAF yang bertugas. Bila ada pertanyaan, Anda bisa menanyakan Help Desk DLAF &nbsp;terlebih dahulu<br>\n<br>\nTerima Kasih!&nbsp;</p>","emailMessage/Importance":"Normal"},"authentication":{"value":"@json(decodeBase64(triggerOutputs().headers['X-MS-APIM-Tokens']))['$ConnectionKey']","type":"Raw"}}},"Initialize_variable_14":{"runAfter":{"Initialize_variable_13":["Succeeded"]},"metadata":{"operationMetadataId":"5f71d45a-6069-48eb-b77a-6697eae9a198"},"type":"InitializeVariable","inputs":{"variables":[{"name":"Submission Time","type":"string","value":"@triggerBody()['text_13']"}]}},"Initialize_variable_15":{"runAfter":{"Initialize_variable_14":["Succeeded"]},"metadata":{"operationMetadataId":"7e3eeeeb-577b-43d0-bb76-b8d8c6c2a9b8"},"type":"InitializeVariable","inputs":{"variables":[{"name":"Telly","type":"string","value":"@triggerBody()['text_14']"}]}}}},"connectionReferences":{"shared_sharepointonline":{"connectionName":"shared-sharepointonl-e74b1b18-9480-4911-a338-088a415ef1dd","source":"Invoker","id":"/providers/Microsoft.PowerApps/apis/shared_sharepointonline","tier":"NotSpecified"},"shared_office365":{"connectionName":"shared-office365-861576d9-8bf9-474f-8667-7e95f8dee9fb","source":"Invoker","id":"/providers/Microsoft.PowerApps/apis/shared_office365","tier":"NotSpecified"}},"flowFailureAlertSubscribed":false,"isManaged":false}}